MANIFEST.in
README.md
requirements.txt
setup.py
subdown2/__init__.py
subdown2/download.py
subdown2/gui.py
subdown2/log.py
subdown2/memegrab.py
subdown2.egg-info/PKG-INFO
subdown2.egg-info/SOURCES.txt
subdown2.egg-info/dependency_links.txt
subdown2.egg-info/entry_points.txt
subdown2.egg-info/requires.txt
subdown2.egg-info/top_level.txt