Metadata-Version: 1.1
Name: subdown2
Version: 0.7.0
Summary: A script that automatically downloads all images from a certain subreddit.
Home-page: https://github.com/legoktm/subdown2/
Author: Kunal Mehta
Author-email: legoktm@gmail.com
License: MIT License
Platform: UNKNOWN
Classifier: License :: OSI Approved :: MIT License
Classifier: Operating System :: MacOS :: MacOS X
Classifier: Operating System :: Microsoft :: Windows
Classifier: Operating System :: POSIX
Classifier: Intended Audience :: End Users/Desktop
Classifier: Environment :: Console
Classifier: Programming Language :: Python
